<?xml version="1.0" encoding="UTF-8"?>
<!DOCTYPE generatorConfiguration
        PUBLIC "-//mybatis.org//DTD MyBatis Generator Configuration 1.0//EN"
        "http://mybatis.org/dtd/mybatis-generator-config_1_0.dtd">
<generatorConfiguration>
    <context id="Mysql" targetRuntime="MyBatis3" defaultModelType="flat">
        <property name="beginningDelimiter" value="`"/>
        <property name="endingDelimiter" value="`"/>
        <property name="javaFileEncoding" value="UTF-8"/>

        <commentGenerator>
            <property name="suppressAllComments" value="true"></property>
            <property name="suppressDate" value="true"></property>
            <property name="javaFileEncoding" value="utf-8"/>
        </commentGenerator>

        <!--        <jdbcConnection driverClass="com.mysql.cj.jdbc.Driver"-->
        <!--                        connectionURL="jdbc:mysql://10.50.17.10:3306/saas?useUnicode=true;characterEncoding=utf8"-->
        <!--                        userId="saasopr"-->
        <!--                        password="Only4SaasApp!">-->
        <!--        </jdbcConnection>-->

        <jdbcConnection driverClass="com.mysql.cj.jdbc.Driver"
                        connectionURL="jdbc:mysql://10.50.17.10:3306/stdcmp?useUnicode=true;characterEncoding=utf8"
                        userId="stdcmpopr"
                        password="Only4StdcmpApp!" />

        <javaTypeResolver>
            <property name="forceBigDecimals" value="true"/>
        </javaTypeResolver>

        <javaModelGenerator targetPackage="com.ligq.study.mybatis.demo.model" targetProject="src/main/java"/>
        <sqlMapGenerator targetPackage="mybatis" targetProject="src/main/resources"/>
        <javaClientGenerator targetPackage="com.ligq.study.mybatis.demo.dao" targetProject="src/main/java"
                             type="XMLMAPPER"/>
        <!-- sql占位符，表示所有的表 -->
        <!--        <table tableName="t_deal_repay_apply"/>-->
<!--                <table tableName="t_product_info"/>-->
<!--                <table tableName="t_credit_reject_code"/>-->
        <!--        <table tableName="T_CREDIT_APPLY_FUND"/>-->
<!--                <table tableName="lacc_duebill_info"/>-->
<!--                <table tableName="lacc_repay_record"/>-->
<!--                <table tableName="lacc_repay_plan"/>-->
<!--                <table tableName="lacc_repay_plan_his"/>-->
<!--                <table tableName="t_credit_limit_log"/>-->
        <!--        <table tableName="t_opr_base_log"/>-->
        <!--        <table tableName="T_CREDIT_APPLY_NODE_INFO"/>-->
<!--                <table tableName="t_customer_base"/>-->
        <!--        <table tableName="T_CUSTOMER_LEGAL"/>-->
        <!--        <table tableName="T_CUSTOMER_PERSON_DETAIL"/>-->
        <!--        <table tableName="T_CUSTOMER_LOGIN_INFO"/>-->

<!--        <table tableName="t_property_info"/>-->
<!--        <table tableName="t_credit_limit_info"/>-->
<!--        <table tableName="t_credit_limit_log"/>-->
<!--                <table tableName="t_credit_apply_log"/>-->

        <!--        <table tableName="t_deal_cusdis_info"/>-->
<!--        <table tableName="t_customer_settleacc_info"/>-->
<!--        <table tableName="t_base_bank_info"/>-->
<!--        <table tableName="t_base_area_city"/>-->
<!--        <table tableName="t_customer_card_info"/>-->
<!--        <table tableName="t_product_info"/>-->
<!--        <table tableName="t_product_introduce"/>-->
<!--        <table tableName="T_SALES_USER_INFO"></table>-->
<!--        <table tableName="t_notice_template"></table>-->
<!--        <table tableName="t_opr_param"></table>-->
<!--        <table tableName="T_SALES_USER_LOGIN_LOG"></table>-->
<!--        <table tableName="T_SALES_USER_MKT_LIST"></table>-->
<!--        <table tableName="t_customer_group_info"></table>-->
<!--        <table tableName="t_customer_social_ref"></table>-->
<!--        <table tableName="t_customer_related_ent_info"></table>-->
<!--        <table tableName="t_customer_label"></table>-->
        <table tableName="t_notice_template"></table>
<!--        <table tableName="t_credit_apply_node_info"></table>-->
<!--        <table tableName="t_customer_auth_log"></table>-->
<!--        <table tableName="t_credit_marketing_rate_info"></table>-->
<!--        <table tableName="temp_interest_discount_cust"></table>-->
<!--        <table tableName="t_credit_limit_info"></table>-->
<!--        <table tableName="T_SALES_USER_INFO"></table>-->
<!--        <table tableName="T_SALES_USER_LESSEE"></table>-->
<!--        <table tableName="T_SALES_USER_LESSEE"></table>-->
<!--        <table tableName="T_LESSEE_BRANCH"></table>-->
<!--        <table tableName="T_OPR_FILE_BATCH"></table>-->

<!--        <table tableName="T_A001_SALES_USER_INFO"></table>-->
<!--        <table tableName="T_A001_SALES_USER_LOGIN_LOG"></table>-->
<!--        <table tableName="t_product_supply_info_step"/>-->
<!--        <table tableName="t_customer_product_supply_log"/>-->
<!--        <table tableName="t_customer_group_info"/>-->
<!--        <table tableName="t_customer_label"/>-->
    </context>
</generatorConfiguration>